easypost/__init__.py
easypost/constant.py
easypost/easypost_client.py
easypost/easypost_object.py
easypost/py.typed
easypost/requestor.py
easypost/util.py
easypost/errors/__init__.py
easypost/errors/api/__init__.py
easypost/errors/api/api_error.py
easypost/errors/api/bad_request_error.py
easypost/errors/api/encoding_error.py
easypost/errors/api/external_api_error.py
easypost/errors/api/forbidden_error.py
easypost/errors/api/gateway_timeout_error.py
easypost/errors/api/http_error.py
easypost/errors/api/internal_server_error.py
easypost/errors/api/invalid_request_error.py
easypost/errors/api/json_error.py
easypost/errors/api/method_not_allowed_error.py
easypost/errors/api/not_found_error.py
easypost/errors/api/payment_error.py
easypost/errors/api/rate_limit_error.py
easypost/errors/api/redirect_error.py
easypost/errors/api/service_unavailable_error.py
easypost/errors/api/timeout_error.py
easypost/errors/api/unauthorized_error.py
easypost/errors/api/unknown_api_error.py
easypost/errors/general/__init__.py
easypost/errors/general/easypost_error.py
easypost/errors/general/end_of_pagination_error.py
easypost/errors/general/filtering_error.py
easypost/errors/general/invalid_object_error.py
easypost/errors/general/invalid_parameter_error.py
easypost/errors/general/missing_parameter_error.py
easypost/errors/general/signature_verification_error.py
easypost/hooks/__init__.py
easypost/hooks/event_hook.py
easypost/hooks/request_hook.py
easypost/hooks/response_hook.py
easypost/models/__init__.py
easypost/models/address.py
easypost/models/api_key.py
easypost/models/batch.py
easypost/models/billing.py
easypost/models/brand.py
easypost/models/carrier_account.py
easypost/models/claim.py
easypost/models/customs_info.py
easypost/models/customs_item.py
easypost/models/end_shipper.py
easypost/models/event.py
easypost/models/insurance.py
easypost/models/order.py
easypost/models/parcel.py
easypost/models/payload.py
easypost/models/pickup.py
easypost/models/pickup_rate.py
easypost-10.2.0.dist-info/licenses/LICENSE
easypost-10.2.0.dist-info/METADATA
easypost-10.2.0.dist-info/WHEEL
easypost-10.2.0.dist-info/top_level.txt
easypost-10.2.0.dist-info/RECORD
