Metadata-Version: 2.4
Name: easypost
Version: 10.2.0
Summary: EasyPost Shipping API Client Library for Python
Home-page: https://easypost.com/
Author: EasyPost
Author-email: support@easypost.com
Project-URL: Docs, https://docs.easypost.com
Project-URL: Tracker, https://github.com/EasyPost/easypost-python/issues
Project-URL: Source, https://github.com/EasyPost/easypost-python
Classifier: Development Status :: 5 - Production/Stable
Classifier: Environment :: Web Environment
Classifier: Programming Language :: Python
Classifier: Programming Language :: Python :: 3.9
Classifier: Programming Language :: Python :: 3.10
Classifier: Programming Language :: Python :: 3.11
Classifier: Programming Language :: Python :: 3.12
Classifier: Programming Language :: Python :: 3.13
Classifier: Intended Audience :: Developers
Classifier: Operating System :: OS Independent
Classifier: License :: OSI Approved :: MIT License
Classifier: Topic :: Software Development :: Libraries
Requires-Python: >=3.9, <4
License-File: LICENSE
Requires-Dist: requests>=2.4.3
Provides-Extra: dev
Requires-Dist: bandit==1.8.*; extra == "dev"
Requires-Dist: black==25.*; extra == "dev"
Requires-Dist: build==1.2.*; extra == "dev"
Requires-Dist: flake8==6.*; extra == "dev"
Requires-Dist: isort==6.*; extra == "dev"
Requires-Dist: mypy==1.15.*; extra == "dev"
Requires-Dist: pdoc==15.*; extra == "dev"
Requires-Dist: pytest-cov==6.*; extra == "dev"
Requires-Dist: pytest-vcr==1.*; extra == "dev"
Requires-Dist: pytest==8.*; extra == "dev"
Requires-Dist: vcrpy==7.*; extra == "dev"
Dynamic: author
Dynamic: author-email
Dynamic: classifier
Dynamic: description
Dynamic: description-content-type
Dynamic: home-page
Dynamic: license-file
Dynamic: project-url
Dynamic: provides-extra
Dynamic: requires-dist
Dynamic: requires-python
Dynamic: summary
